Workbook

Sheet README
A1: Northgate Constructors Ltd. — Synthetic Corporate Finance Dataset
A3: PURPOSE: Practice / portfolio dataset for building a WIP & project financial dashboard in Power BI.
A4: ALL DATA IS FICTIONAL. Generated for demonstration purposes — no real company, client, or project data.
A6: SHEETS:
A7: Projects — master list: contract values, revised values (orig + approved COs), current cost estimates
A8: Job_Cost_Detail — monthly costs by project and category (Labour / Materials / Subcontracts / Equipment)
A9: Billings — monthly progress billings by project
A10: Change_Orders — CO register with Approved / Pending status (only Approved COs revise contract value)
A11: WIP_Schedule — live percentage-of-completion schedule built from the sheets above (all formulas)
A13: KEY CONCEPTS (percentage-of-completion method):
A14: % Complete = Cost to Date / Estimated Total Cost
A15: Earned Revenue = % Complete x Revised Contract Value
... A20: approved vs pending CO exposure · cost mix by category · revenue by client / sector / district

Sheet Projects
A1: Project ID | B1: Project Name | C1: Client | D1: Sector | E1: District | F1: Original Contract Value | G1: Approved Change Orders | H1: Revised Contract Value | I1: Estimated Total Cost (Current)
A2: P-101 | B2: Riverbend Water Treatment Expansion | C2: City of Meadowvale | D2: Civil | E2: Prairies | F2: 48500000 | G2: =SUMIFS(Change_Orders!F:F,Change_Orders!A:A,A2,Change_Orders!E:E,"Approved") -> 0 | H2: =F2+G2 -> 48500000 | I2: 44620000
A3: P-102 | B3: Aurora Logistics Distribution Centre | C3: NorthStar Logistics | D3: Buildings | E3: Prairies | F3: 23400000 | G3: =SUMIFS(Change_Orders!F:F,Change_Orders!A:A,A3,Change_Orders!E:E,"Approved") -> 1199000 | H3: =F3+G3 -> 24599000 | I3: 22877000
A4: P-103 | B4: Kestrel Ridge Wind Farm BOP | C4: Kestrel Renewables | D4: Industrial | E4: Prairies | F4: 86000000 | G4: =SUMIFS(Change_Orders!F:F,Change_Orders!A:A,A4,Change_Orders!E:E,"Approved") -> 0 | H4: =F4+G4 -> 86000000 | I4: 80840000
A5: P-104 | B5: St. Bridget Hospital Renovation Ph2 | C5: Vantage Health Partners | D5: Buildings | E5: Mountain | F5: 31750000 | G5: =SUMIFS(Change_Orders!F:F,Change_Orders!A:A,A5,Change_Orders!E:E,"Approved") -> 0 | H5: =F5+G5 -> 31750000 | I5: 28892000
A6: P-105 | B6: Coyote Flats Gas Processing Module | C6: TriPeak Midstream | D6: Industrial | E6: Mountain | F6: 112000000 | G6: =SUMIFS(Change_Orders!F:F,Change_Orders!A:A,A6,Change_Orders!E:E,"Approved") -> 6424000 | H6: =F6+G6 -> 118424000 | I6: 112503000
A7: P-106 | B7: Larkspur Transit Garage | C7: Metro Transit Authority | D7: Civil | E7: Pacific | F7: 19800000 | G7: =SUMIFS(Change_Orders!F:F,Change_Orders!A:A,A7,Change_Orders!E:E,"Approved") -> 1346000 | H7: =F7+G7 -> 21146000 | I7: 20723000
A8: P-107 | B8: Meridian Office Tower Fit-Out | C8: Meridian Properties | D8: Buildings | E8: Pacific | F8: 12600000 | G8: =SUMIFS(Change_Orders!F:F,Change_Orders!A:A,A8,Change_Orders!E:E,"Approved") -> 411000 | H8: =F8+G8 -> 13011000 | I8: 11450000
A9: P-108 | B9: Signal Hill Substation Upgrade | C9: Prairie Grid Corp | D9: Industrial | E9: Prairies | F9: 27300000 | G9: =SUMIFS(Change_Orders!F:F,Change_Orders!A:A,A9,Change_Orders!E:E,"Approved") -> 0 | H9: =F9+G9 -> 27300000 | I9: 25116000

Sheet Job_Cost_Detail
A1: Month End | B1: Project ID | C1: Cost Category | D1: Amount
A2: 45866 | B2: P-101 | C2: Labour | D2: 606568
A3: 45866 | B3: P-101 | C3: Materials | D3: 522598
A4: 45866 | B4: P-101 | C4: Subcontracts | D4: 337902
A5: 45866 | B5: P-101 | C5: Equipment | D5: 152722
A6: 45897 | B6: P-101 | C6: Labour | D6: 838626
A7: 45897 | B7: P-101 | C7: Materials | D7: 806004
A8: 45897 | B8: P-101 | C8: Subcontracts | D8: 521437
A9: 45897 | B9: P-101 | C9: Equipment | D9: 234297
A10: 45928 | B10: P-101 | C10: Labour | D10: 873518
A11: 45928 | B11: P-101 | C11: Materials | D11: 604742
A12: 45928 | B12: P-101 | C12: Subcontracts | D12: 403708
A13: 45928 | B13: P-101 | C13: Equipment | D13: 253576
... A385: 46201 | B385: P-108 | C385: Equipment | D385: 51763

Sheet Billings
A1: Month End | B1: Project ID | C1: Amount Billed
A2: 45866 | B2: P-101 | C2: 1885600
A3: 45897 | B3: P-101 | C3: 2861100
A4: 45928 | B4: P-101 | C4: 2596400
A5: 45958 | B5: P-101 | C5: 4457700
A6: 46050 | B6: P-101 | C6: 1892700
A7: 46081 | B7: P-101 | C7: 2908300
A8: 46109 | B8: P-101 | C8: 1914800
A9: 46140 | B9: P-101 | C9: 2290200
A10: 46170 | B10: P-101 | C10: 3682400
A11: 46201 | B11: P-101 | C11: 1811000
A12: 45866 | B12: P-102 | C12: 1419200
A13: 45897 | B13: P-102 | C13: 2013000
... A88: 46201 | B88: P-108 | C88: 691200

Sheet Change_Orders
A1: Project ID | B1: CO # | C1: Date | D1: Description | E1: Status | F1: Amount
A2: P-102 | B2: CO-01 | C2: 45989 | D2: Added electrical scope | E2: Approved | F2: 477000
A3: P-102 | B3: CO-02 | C3: 45958 | D3: Differing site conditions | E3: Approved | F3: 567000
A4: P-102 | B4: CO-03 | C4: 46109 | D4: Added electrical scope | E4: Pending | F4: 696000
A5: P-102 | B5: CO-04 | C5: 46140 | D5: Added electrical scope | E5: Approved | F5: 155000
A6: P-104 | B6: CO-01 | C6: 46050 | D6: Added electrical scope | E6: Pending | F6: 697000
A7: P-105 | B7: CO-01 | C7: 45958 | D7: Design revision | E7: Approved | F7: 1969000
A8: P-105 | B8: CO-02 | C8: 45928 | D8: Owner-directed scope addition | E8: Approved | F8: 1268000
A9: P-105 | B9: CO-03 | C9: 46081 | D9: Schedule acceleration | E9: Approved | F9: 3187000
A10: P-105 | B10: CO-04 | C10: 45958 | D10: Schedule acceleration | E10: Pending | F10: 3232000
A11: P-106 | B11: CO-01 | C11: 46140 | D11: Schedule acceleration | E11: Approved | F11: 441000
A12: P-106 | B12: CO-02 | C12: 46050 | D12: Added electrical scope | E12: Approved | F12: 290000
A13: P-106 | B13: CO-03 | C13: 46050 | D13: Schedule acceleration | E13: Approved | F13: 473000
... A17: P-107 | B17: CO-03 | C17: 45958 | D17: Added electrical scope | E17: Approved | F17: 411000

Sheet WIP_Schedule
A1: Project ID | B1: Project Name | C1: Revised Contract Value | D1: Est. Total Cost | E1: Cost to Date | F1: % Complete | G1: Earned Revenue | H1: Billed to Date | I1: Over/(Under) Billing | J1: Est. Gross Profit | K1: Est. GP % | L1: Cost to Complete
A2: =Projects!A2 -> P-101 | B2: =Projects!B2 -> Riverbend Water Treatment Expansion | C2: =Projects!H2 -> 48500000 | D2: =Projects!I2 -> 44620000 | E2: =SUMIFS(Job_Cost_Detail!D:D,Job_Cost_Detail!B:B,A2) -> 32250636 | F2: =IF(D2=0,0,E2/D2) -> 0.72278431 | G2: =F2*C2 -> 35055039 | H2: =SUMIFS(Billings!C:C,Billings!B:B,A2) -> 26300200 | I2: =H2-G2 -> -8754839.1 | J2: =C2-D2 -> 3880000 | K2: =IF(C2=0,0,J2/C2) -> 0.08 | L2: =D2-E2 -> 12369364
A3: =Projects!A3 -> P-102 | B3: =Projects!B3 -> Aurora Logistics Distribution Centre | C3: =Projects!H3 -> 24599000 | D3: =Projects!I3 -> 22877000 | E3: =SUMIFS(Job_Cost_Detail!D:D,Job_Cost_Detail!B:B,A3) -> 22441975 | F3: =IF(D3=0,0,E3/D3) -> 0.98098418 | G3: =F3*C3 -> 24131230 | H3: =SUMIFS(Billings!C:C,Billings!B:B,A3) -> 21173500 | I3: =H3-G3 -> -2957729.8 | J3: =C3-D3 -> 1722000 | K3: =IF(C3=0,0,J3/C3) -> 0.070002846 | L3: =D3-E3 -> 435025
A4: =Projects!A4 -> P-103 | B4: =Projects!B4 -> Kestrel Ridge Wind Farm BOP | C4: =Projects!H4 -> 86000000 | D4: =Projects!I4 -> 80840000 | E4: =SUMIFS(Job_Cost_Detail!D:D,Job_Cost_Detail!B:B,A4) -> 33561395 | F4: =IF(D4=0,0,E4/D4) -> 0.41515828 | G4: =F4*C4 -> 35703612 | H4: =SUMIFS(Billings!C:C,Billings!B:B,A4) -> 30258300 | I4: =H4-G4 -> -5445311.7 | J4: =C4-D4 -> 5160000 | K4: =IF(C4=0,0,J4/C4) -> 0.06 | L4: =D4-E4 -> 47278605
A5: =Projects!A5 -> P-104 | B5: =Projects!B5 -> St. Bridget Hospital Renovation Ph2 | C5: =Projects!H5 -> 31750000 | D5: =Projects!I5 -> 28892000 | E5: =SUMIFS(Job_Cost_Detail!D:D,Job_Cost_Detail!B:B,A5) -> 18010990 | F5: =IF(D5=0,0,E5/D5) -> 0.62339021 | G5: =F5*C5 -> 19792639 | H5: =SUMIFS(Billings!C:C,Billings!B:B,A5) -> 19221300 | I5: =H5-G5 -> -571339.23 | J5: =C5-D5 -> 2858000 | K5: =IF(C5=0,0,J5/C5) -> 0.090015748 | L5: =D5-E5 -> 10881010
A6: =Projects!A6 -> P-105 | B6: =Projects!B6 -> Coyote Flats Gas Processing Module | C6: =Projects!H6 -> 118424000 | D6: =Projects!I6 -> 112503000 | E6: =SUMIFS(Job_Cost_Detail!D:D,Job_Cost_Detail!B:B,A6) -> 62548395 | F6: =IF(D6=0,0,E6/D6) -> 0.55597091 | G6: =F6*C6 -> 65840299 | H6: =SUMIFS(Billings!C:C,Billings!B:B,A6) -> 66950500 | I6: =H6-G6 -> 1110201.3 | J6: =C6-D6 -> 5921000 | K6: =IF(C6=0,0,J6/C6) -> 0.049998311 | L6: =D6-E6 -> 49954605
A7: =Projects!A7 -> P-106 | B7: =Projects!B7 -> Larkspur Transit Garage | C7: =Projects!H7 -> 21146000 | D7: =Projects!I7 -> 20723000 | E7: =SUMIFS(Job_Cost_Detail!D:D,Job_Cost_Detail!B:B,A7) -> 18336721 | F7: =IF(D7=0,0,E7/D7) -> 0.88484877 | G7: =F7*C7 -> 18711012 | H7: =SUMIFS(Billings!C:C,Billings!B:B,A7) -> 18883600 | I7: =H7-G7 -> 172587.97 | J7: =C7-D7 -> 423000 | K7: =IF(C7=0,0,J7/C7) -> 0.020003783 | L7: =D7-E7 -> 2386279
A8: =Projects!A8 -> P-107 | B8: =Projects!B8 -> Meridian Office Tower Fit-Out | C8: =Projects!H8 -> 13011000 | D8: =Projects!I8 -> 11450000 | E8: =SUMIFS(Job_Cost_Detail!D:D,Job_Cost_Detail!B:B,A8) -> 4000080 | F8: =IF(D8=0,0,E8/D8) -> 0.34935197 | G8: =F8*C8 -> 4545418.4 | H8: =SUMIFS(Billings!C:C,Billings!B:B,A8) -> 3893100 | I8: =H8-G8 -> -652318.42 | J8: =C8-D8 -> 1561000 | K8: =IF(C8=0,0,J8/C8) -> 0.11997541 | L8: =D8-E8 -> 7449920
A9: =Projects!A9 -> P-108 | B9: =Projects!B9 -> Signal Hill Substation Upgrade | C9: =Projects!H9 -> 27300000 | D9: =Projects!I9 -> 25116000 | E9: =SUMIFS(Job_Cost_Detail!D:D,Job_Cost_Detail!B:B,A9) -> 5038547 | F9: =IF(D9=0,0,E9/D9) -> 0.20061104 | G9: =F9*C9 -> 5476681.5 | H9: =SUMIFS(Billings!C:C,Billings!B:B,A9) -> 4725200 | I9: =H9-G9 -> -751481.52 | J9: =C9-D9 -> 2184000 | K9: =IF(C9=0,0,J9/C9) -> 0.08 | L9: =D9-E9 -> 20077453
B10: TOTAL | C10: =SUM(C2:C9) -> 370730000 | D10: =SUM(D2:D9) -> 347021000 | E10: =SUM(E2:E9) -> 196188739 | F10: =IF(D10=0,0,E10/D10) -> 0.5653512 | G10: =SUM(G2:G9) -> 2.0925593e+08 | H10: =SUM(H2:H9) -> 191405700 | I10: =SUM(I2:I9) -> -17850231 | J10: =SUM(J2:J9) -> 23709000 | K10: =IF(C10=0,0,J10/C10) -> 0.063952202 | L10: =SUM(L2:L9) -> 150832261
B12: All formulas — nothing hardcoded. Source data: Projects / Job_Cost_Detail / Billings / Change_Orders sheets.
